{
  "account": {
    "id": "d08df475-4646-4098-bfc6-6d2613252499",
    "cash": 16425.08,
    "portfolio_value": 134144.81,
    "buying_power": 150569.89,
    "currency": "USD",
    "account_status": "ACTIVE",
    "trading_blocked": false,
    "equity": 134144.81,
    "updated_at": "2026-04-02T17:07:34.981071"
  },
  "positions": [
    {
      "symbol": "ALB",
      "qty": 175.0,
      "market_value": 31295.25,
      "cost_basis": 10018.75,
      "unrealized_pl": 21276.5,
      "unrealized_plpc": 2.12367,
      "current_price": 178.83,
      "avg_entry_price": 57.25,
      "side": "long",
      "exchange": "NYSE"
    },
    {
      "symbol": "JNJ",
      "qty": 34.0,
      "market_value": 8301.78,
      "cost_basis": 5060.849986,
      "unrealized_pl": 3240.930014,
      "unrealized_plpc": 0.64039,
      "current_price": 244.17,
      "avg_entry_price": 148.848529,
      "side": "long",
      "exchange": "NYSE"
    },
    {
      "symbol": "KO",
      "qty": 99.0,
      "market_value": 7589.6271,
      "cost_basis": 7053.75,
      "unrealized_pl": 535.8771,
      "unrealized_plpc": 0.07597,
      "current_price": 76.6629,
      "avg_entry_price": 71.25,
      "side": "long",
      "exchange": "NYSE"
    },
    {
      "symbol": "LMT",
      "qty": 16.0,
      "market_value": 9948.88,
      "cost_basis": 7540.72,
      "unrealized_pl": 2408.16,
      "unrealized_plpc": 0.31935,
      "current_price": 621.805,
      "avg_entry_price": 471.295,
      "side": "long",
      "exchange": "NYSE"
    },
    {
      "symbol": "MRK",
      "qty": 108.0,
      "market_value": 12918.96,
      "cost_basis": 8377.209972,
      "unrealized_pl": 4541.750028,
      "unrealized_plpc": 0.54216,
      "current_price": 119.62,
      "avg_entry_price": 77.566759,
      "side": "long",
      "exchange": "NYSE"
    },
    {
      "symbol": "NEE",
      "qty": 21.0,
      "market_value": 1954.89,
      "cost_basis": 1475.25,
      "unrealized_pl": 479.64,
      "unrealized_plpc": 0.32512,
      "current_price": 93.09,
      "avg_entry_price": 70.25,
      "side": "long",
      "exchange": "NYSE"
    },
    {
      "symbol": "O",
      "qty": 180.0,
      "market_value": 11224.8,
      "cost_basis": 9945.0,
      "unrealized_pl": 1279.8,
      "unrealized_plpc": 0.12869,
      "current_price": 62.36,
      "avg_entry_price": 55.25,
      "side": "long",
      "exchange": "NYSE"
    },
    {
      "symbol": "PFE",
      "qty": 155.0,
      "market_value": 4393.475,
      "cost_basis": 3526.25,
      "unrealized_pl": 867.225,
      "unrealized_plpc": 0.24593,
      "current_price": 28.345,
      "avg_entry_price": 22.75,
      "side": "long",
      "exchange": "NYSE"
    },
    {
      "symbol": "PGR",
      "qty": 27.0,
      "market_value": 5278.77,
      "cost_basis": 7549.799994,
      "unrealized_pl": -2271.029994,
      "unrealized_plpc": -0.30081,
      "current_price": 195.51,
      "avg_entry_price": 279.622222,
      "side": "long",
      "exchange": "NYSE"
    },
    {
      "symbol": "TROW",
      "qty": 100.0,
      "market_value": 8958.0,
      "cost_basis": 9547.0,
      "unrealized_pl": -589.0,
      "unrealized_plpc": -0.06169,
      "current_price": 89.58,
      "avg_entry_price": 95.47,
      "side": "long",
      "exchange": "NASDAQ"
    },
    {
      "symbol": "UGI",
      "qty": 145.0,
      "market_value": 5327.3,
      "cost_basis": 5038.75,
      "unrealized_pl": 288.55,
      "unrealized_plpc": 0.05727,
      "current_price": 36.74,
      "avg_entry_price": 34.75,
      "side": "long",
      "exchange": "NYSE"
    },
    {
      "symbol": "VZ",
      "qty": 175.0,
      "market_value": 8643.25,
      "cost_basis": 7420.0,
      "unrealized_pl": 1223.25,
      "unrealized_plpc": 0.16486,
      "current_price": 49.39,
      "avg_entry_price": 42.4,
      "side": "long",
      "exchange": "NYSE"
    },
    {
      "symbol": "WMT",
      "qty": 15.0,
      "market_value": 1884.75,
      "cost_basis": 1458.75,
      "unrealized_pl": 426.0,
      "unrealized_plpc": 0.29203,
      "current_price": 125.65,
      "avg_entry_price": 97.25,
      "side": "long",
      "exchange": "NASDAQ"
    }
  ],
  "cash": 16425.08,
  "timestamp": "2026-04-02T17:07:35.008789"
}