{
  "account": {
    "id": "d08df475-4646-4098-bfc6-6d2613252499",
    "cash": 16425.08,
    "portfolio_value": 131151.36,
    "buying_power": 147576.44,
    "currency": "USD",
    "account_status": "ACTIVE",
    "trading_blocked": false,
    "equity": 131151.36,
    "updated_at": "2026-03-16T05:43:57.664878"
  },
  "positions": [
    {
      "symbol": "ALB",
      "qty": 175.0,
      "market_value": 27681.5,
      "cost_basis": 10018.75,
      "unrealized_pl": 17662.75,
      "unrealized_plpc": 1.76297,
      "current_price": 158.18,
      "avg_entry_price": 57.25,
      "side": "long",
      "exchange": "NYSE"
    },
    {
      "symbol": "JNJ",
      "qty": 34.0,
      "market_value": 8180.74,
      "cost_basis": 5060.849986,
      "unrealized_pl": 3119.890014,
      "unrealized_plpc": 0.61648,
      "current_price": 240.61,
      "avg_entry_price": 148.848529,
      "side": "long",
      "exchange": "NYSE"
    },
    {
      "symbol": "KO",
      "qty": 99.0,
      "market_value": 7652.7,
      "cost_basis": 7053.75,
      "unrealized_pl": 598.95,
      "unrealized_plpc": 0.08491,
      "current_price": 77.3,
      "avg_entry_price": 71.25,
      "side": "long",
      "exchange": "NYSE"
    },
    {
      "symbol": "LMT",
      "qty": 16.0,
      "market_value": 10324.8,
      "cost_basis": 7540.72,
      "unrealized_pl": 2784.08,
      "unrealized_plpc": 0.36921,
      "current_price": 645.3,
      "avg_entry_price": 471.295,
      "side": "long",
      "exchange": "NYSE"
    },
    {
      "symbol": "MRK",
      "qty": 108.0,
      "market_value": 12417.84,
      "cost_basis": 8377.209972,
      "unrealized_pl": 4040.630028,
      "unrealized_plpc": 0.48234,
      "current_price": 114.98,
      "avg_entry_price": 77.566759,
      "side": "long",
      "exchange": "NYSE"
    },
    {
      "symbol": "NEE",
      "qty": 21.0,
      "market_value": 1960.35,
      "cost_basis": 1475.25,
      "unrealized_pl": 485.1,
      "unrealized_plpc": 0.32883,
      "current_price": 93.35,
      "avg_entry_price": 70.25,
      "side": "long",
      "exchange": "NYSE"
    },
    {
      "symbol": "O",
      "qty": 180.0,
      "market_value": 11608.2,
      "cost_basis": 9945.0,
      "unrealized_pl": 1663.2,
      "unrealized_plpc": 0.16724,
      "current_price": 64.49,
      "avg_entry_price": 55.25,
      "side": "long",
      "exchange": "NYSE"
    },
    {
      "symbol": "PFE",
      "qty": 155.0,
      "market_value": 4123.0,
      "cost_basis": 3526.25,
      "unrealized_pl": 596.75,
      "unrealized_plpc": 0.16923,
      "current_price": 26.6,
      "avg_entry_price": 22.75,
      "side": "long",
      "exchange": "NYSE"
    },
    {
      "symbol": "PGR",
      "qty": 27.0,
      "market_value": 5535.0,
      "cost_basis": 7549.799994,
      "unrealized_pl": -2014.799994,
      "unrealized_plpc": -0.26687,
      "current_price": 205.0,
      "avg_entry_price": 279.622222,
      "side": "long",
      "exchange": "NYSE"
    },
    {
      "symbol": "TROW",
      "qty": 100.0,
      "market_value": 8986.0,
      "cost_basis": 9547.0,
      "unrealized_pl": -561.0,
      "unrealized_plpc": -0.05876,
      "current_price": 89.86,
      "avg_entry_price": 95.47,
      "side": "long",
      "exchange": "NASDAQ"
    },
    {
      "symbol": "UGI",
      "qty": 145.0,
      "market_value": 5383.85,
      "cost_basis": 5038.75,
      "unrealized_pl": 345.1,
      "unrealized_plpc": 0.06849,
      "current_price": 37.13,
      "avg_entry_price": 34.75,
      "side": "long",
      "exchange": "NYSE"
    },
    {
      "symbol": "VZ",
      "qty": 175.0,
      "market_value": 8977.5,
      "cost_basis": 7420.0,
      "unrealized_pl": 1557.5,
      "unrealized_plpc": 0.20991,
      "current_price": 51.3,
      "avg_entry_price": 42.4,
      "side": "long",
      "exchange": "NYSE"
    },
    {
      "symbol": "WMT",
      "qty": 15.0,
      "market_value": 1894.8,
      "cost_basis": 1458.75,
      "unrealized_pl": 436.05,
      "unrealized_plpc": 0.29892,
      "current_price": 126.32,
      "avg_entry_price": 97.25,
      "side": "long",
      "exchange": "NASDAQ"
    }
  ],
  "cash": 16425.08,
  "timestamp": "2026-03-16T05:43:57.694278"
}