{
  "account": {
    "id": "d08df475-4646-4098-bfc6-6d2613252499",
    "cash": 16425.08,
    "portfolio_value": 131993.38,
    "buying_power": 148418.46,
    "currency": "USD",
    "account_status": "ACTIVE",
    "trading_blocked": false,
    "equity": 131993.38,
    "updated_at": "2026-02-07T09:14:05.053854"
  },
  "positions": [
    {
      "symbol": "ALB",
      "qty": 175.0,
      "market_value": 28589.75,
      "cost_basis": 10018.75,
      "unrealized_pl": 18571.0,
      "unrealized_plpc": 1.85362,
      "current_price": 163.37,
      "avg_entry_price": 57.25,
      "side": "long",
      "exchange": "NYSE"
    },
    {
      "symbol": "JNJ",
      "qty": 34.0,
      "market_value": 8159.66,
      "cost_basis": 5060.85,
      "unrealized_pl": 3098.81,
      "unrealized_plpc": 0.61231,
      "current_price": 239.99,
      "avg_entry_price": 148.848529,
      "side": "long",
      "exchange": "NYSE"
    },
    {
      "symbol": "KO",
      "qty": 99.0,
      "market_value": 7823.97,
      "cost_basis": 7053.75,
      "unrealized_pl": 770.22,
      "unrealized_plpc": 0.10919,
      "current_price": 79.03,
      "avg_entry_price": 71.25,
      "side": "long",
      "exchange": "NYSE"
    },
    {
      "symbol": "LMT",
      "qty": 16.0,
      "market_value": 9977.28,
      "cost_basis": 7540.72,
      "unrealized_pl": 2436.56,
      "unrealized_plpc": 0.32312,
      "current_price": 623.58,
      "avg_entry_price": 471.295,
      "side": "long",
      "exchange": "NYSE"
    },
    {
      "symbol": "MRK",
      "qty": 108.0,
      "market_value": 13168.44,
      "cost_basis": 8377.21,
      "unrealized_pl": 4791.23,
      "unrealized_plpc": 0.57194,
      "current_price": 121.93,
      "avg_entry_price": 77.566759,
      "side": "long",
      "exchange": "NYSE"
    },
    {
      "symbol": "NEE",
      "qty": 21.0,
      "market_value": 1878.87,
      "cost_basis": 1475.25,
      "unrealized_pl": 403.62,
      "unrealized_plpc": 0.27359,
      "current_price": 89.47,
      "avg_entry_price": 70.25,
      "side": "long",
      "exchange": "NYSE"
    },
    {
      "symbol": "O",
      "qty": 180.0,
      "market_value": 11381.4,
      "cost_basis": 9945.0,
      "unrealized_pl": 1436.4,
      "unrealized_plpc": 0.14443,
      "current_price": 63.23,
      "avg_entry_price": 55.25,
      "side": "long",
      "exchange": "NYSE"
    },
    {
      "symbol": "PFE",
      "qty": 155.0,
      "market_value": 4219.1,
      "cost_basis": 3526.25,
      "unrealized_pl": 692.85,
      "unrealized_plpc": 0.19648,
      "current_price": 27.22,
      "avg_entry_price": 22.75,
      "side": "long",
      "exchange": "NYSE"
    },
    {
      "symbol": "PGR",
      "qty": 27.0,
      "market_value": 5461.83,
      "cost_basis": 7549.8,
      "unrealized_pl": -2087.97,
      "unrealized_plpc": -0.27656,
      "current_price": 202.29,
      "avg_entry_price": 279.622222,
      "side": "long",
      "exchange": "NYSE"
    },
    {
      "symbol": "TROW",
      "qty": 100.0,
      "market_value": 9458.0,
      "cost_basis": 9547.0,
      "unrealized_pl": -89.0,
      "unrealized_plpc": -0.00932,
      "current_price": 94.58,
      "avg_entry_price": 95.47,
      "side": "long",
      "exchange": "NASDAQ"
    },
    {
      "symbol": "UGI",
      "qty": 145.0,
      "market_value": 5378.05,
      "cost_basis": 5038.75,
      "unrealized_pl": 339.3,
      "unrealized_plpc": 0.06734,
      "current_price": 37.09,
      "avg_entry_price": 34.75,
      "side": "long",
      "exchange": "NYSE"
    },
    {
      "symbol": "VZ",
      "qty": 175.0,
      "market_value": 8104.25,
      "cost_basis": 7420.0,
      "unrealized_pl": 684.25,
      "unrealized_plpc": 0.09222,
      "current_price": 46.31,
      "avg_entry_price": 42.4,
      "side": "long",
      "exchange": "NYSE"
    },
    {
      "symbol": "WMT",
      "qty": 15.0,
      "market_value": 1967.7,
      "cost_basis": 1458.75,
      "unrealized_pl": 508.95,
      "unrealized_plpc": 0.34889,
      "current_price": 131.18,
      "avg_entry_price": 97.25,
      "side": "long",
      "exchange": "NASDAQ"
    }
  ],
  "cash": 16425.08,
  "timestamp": "2026-02-07T09:14:05.068091"
}